ol_openedx_chat/__init__.py
ol_openedx_chat/apps.py
ol_openedx_chat/block.py
ol_openedx_chat/compat.py
ol_openedx_chat/constants.py
ol_openedx_chat/urls.py
ol_openedx_chat/utils.py
ol_openedx_chat/settings/common.py
ol_openedx_chat/settings/devstack.py
ol_openedx_chat/static/css/ai_chat.css
ol_openedx_chat/static/css/studio.css
ol_openedx_chat/static/html/student_view.html
ol_openedx_chat/static/html/studio_view.html
ol_openedx_chat/static/images/ai_chat_aside_cms_view.png
ol_openedx_chat/static/images/ai_chat_aside_lms_drawer_view.png
ol_openedx_chat/static/images/ai_chat_aside_lms_view.png
ol_openedx_chat/static/images/icon.svg
ol_openedx_chat/static/js/ai_chat.js
ol_openedx_chat/static/js/studio.js
ol_openedx_chat-0.5.3.dist-info/METADATA
ol_openedx_chat-0.5.3.dist-info/WHEEL
ol_openedx_chat-0.5.3.dist-info/entry_points.txt
ol_openedx_chat-0.5.3.dist-info/licenses/LICENSE.txt
ol_openedx_chat-0.5.3.dist-info/RECORD
