Metadata-Version: 2.4
Name: ol-openedx-chat
Version: 0.5.3
Summary: An Open edX plugin to add Open Learning AI chat aside to xBlocks
Author: MIT Office of Digital Learning
License-Expression: BSD-3-Clause
License-File: LICENSE.txt
Keywords: Python,edx
Requires-Python: >=3.11
Requires-Dist: django>=4.0
Requires-Dist: djangorestframework>=3.14.0
Requires-Dist: edx-django-utils>4.0.0
Requires-Dist: xblock
